othelloai/__init__.py
othelloai/__main__.py
othelloai/ai.py
othelloai/bitboard.py
othelloai/game.py
othelloai/player.py
othelloai/ui.py
othello_ai-0.1.1.dist-info/LICENSE
othello_ai-0.1.1.dist-info/WHEEL
othello_ai-0.1.1.dist-info/METADATA
othello_ai-0.1.1.dist-info/RECORD
