Metadata-Version: 2.1
Name: othello-ai
Version: 0.1.1
Summary: Othello game engine
Home-page: https://github.com/jcarrete5/othello-ai
License: MIT
Keywords: othello,ai
Author: Jason R. Carrete
Author-email: jasoncarrete5@gmail.com
Requires-Python: >=3.7,<4.0
Classifier: License :: OSI Approved :: MIT License
Classifier: Programming Language :: Python :: 3
Classifier: Programming Language :: Python :: 3.7
Project-URL: Repository, https://github.com/jcarrete5/othello-ai
